airflow_powerbi_plugin/__init__.py
airflow_powerbi_plugin/powerbi_plugin.py
airflow_powerbi_plugin/hooks/__init__.py
airflow_powerbi_plugin/hooks/powerbi.py
airflow_powerbi_plugin/operators/__init__.py
airflow_powerbi_plugin/operators/powerbi.py
airflow_powerbi_plugin_custom-1.0.7.dist-info/LICENSE
airflow_powerbi_plugin_custom-1.0.7.dist-info/METADATA
airflow_powerbi_plugin_custom-1.0.7.dist-info/WHEEL
airflow_powerbi_plugin_custom-1.0.7.dist-info/top_level.txt
airflow_powerbi_plugin_custom-1.0.7.dist-info/RECORD
